pc2graph/__init__.py
pc2graph/downsampling.py
pc2graph/shortpath.py
pc2graph-1.0.1.dist-info/LICENSE
pc2graph-1.0.1.dist-info/METADATA
pc2graph-1.0.1.dist-info/WHEEL
pc2graph-1.0.1.dist-info/top_level.txt
pc2graph-1.0.1.dist-info/RECORD
