Metadata-Version: 2.1
Name: pc2graph
Version: 1.0.1
Summary: Generates a NetworkX graph from 3D point clouds acquired using Terrestrial LiDAR Scanners.
Home-page: https://github.com/mattbv/pc2graph
Author: Matheus Boni Vicari
Author-email: matheus.boni.vicari@gmail.com
License: LICENSE.txt
Keywords: networkx graph shortest path TLS point cloud LiDAR
Platform: UNKNOWN
Classifier: Programming Language :: Python
Classifier: Topic :: Scientific/Engineering
Requires-Dist: numpy (>=1.11.3)
Requires-Dist: scikit-learn (>=0.19.1)
Requires-Dist: networkx (>=1.11)
